Metadata-Version: 1.0
Name: bhp-probability
Version: 1.0
Summary: Gaussian and Binomial distributions
Home-page: UNKNOWN
Author: Bach Pham
Author-email: phuybach@gmail.com
License: UNKNOWN
Platform: UNKNOWN
